pyfivetran/__init__.py
pyfivetran/client.py
pyfivetran/endpoints/__init__.py
pyfivetran/endpoints/base.py
pyfivetran/endpoints/certificate.py
pyfivetran/endpoints/connector.py
pyfivetran/endpoints/destination.py
pyfivetran/endpoints/group.py
pyfivetran/endpoints/logs.py
pyfivetran/endpoints/roles.py
pyfivetran/endpoints/schema.py
pyfivetran/endpoints/users.py
pyfivetran/endpoints/webhook.py
pyfivetran/shed.py
pyfivetran/utils.py
pyfivetran-2024.4.26.1.dist-info/METADATA
pyfivetran-2024.4.26.1.dist-info/WHEEL
pyfivetran-2024.4.26.1.dist-info/RECORD
