Metadata-Version: 2.1
Name: pyfivetran
Version: 2024.4.26.1
Summary: Pythonic interface to the fivetran API
License: MIT
Author: Khari Gardner
Author-email: kharigardner@protonmail.com
Requires-Python: >=3.8,<3.12
Classifier: License :: OSI Approved :: MIT License
Classifier: Programming Language :: Python :: 3
Classifier: Programming Language :: Python :: 3.8
Classifier: Programming Language :: Python :: 3.9
Classifier: Programming Language :: Python :: 3.10
Classifier: Programming Language :: Python :: 3.11
Requires-Dist: httpx (>=0.25.1,<0.26.0)
Requires-Dist: lazy (>=1.6,<2.0)
Requires-Dist: python-dateutil (>=2.9.0.post0,<3.0.0)
Requires-Dist: pytz (>=2024.1,<2025.0)
